opticalpy/__init__.py
opticalpy/optgroup.py
opticalpy/optic.py
opticalpy/ray.py
opticalpy/scene.py
opticalpy/utils.py
opticalpy/visualization.py
opticalpy/elems/__init__.py
opticalpy/elems/beam.py
opticalpy/elems/filter.py
opticalpy/elems/grating.py
opticalpy/elems/lens.py
opticalpy/elems/material.py
opticalpy/elems/mirror.py
opticalpy/elems/telescope.py
opticalpy/op3d/__init__.py
opticalpy/op3d/optic.py
opticalpy/op3d/ray.py
opticalpy/op3d/scene.py
opticalpy/op3d/elems/__init__.py
opticalpy/op3d/elems/beam.py
opticalpy/op3d/elems/camera.py
opticalpy/op3d/elems/grating.py
opticalpy/op3d/elems/mirror.py
opticalpy-1.2.0.dist-info/LICENSE
opticalpy-1.2.0.dist-info/METADATA
opticalpy-1.2.0.dist-info/WHEEL
opticalpy-1.2.0.dist-info/top_level.txt
opticalpy-1.2.0.dist-info/RECORD
