Metadata-Version: 2.1
Name: opticalpy
Version: 1.2.0
Summary: Exact geometrical optics including dispersion to learn and design optical instruments
Author-email: Aurélien Genin <aurelien.genin@polytechnique.org>
License:                     GNU GENERAL PUBLIC LICENSE
Project-URL: Source, https://github.com/AstroAure/Opticalpy
Classifier: Programming Language :: Python :: 3
Classifier: License :: OSI Approved :: GNU General Public License v3 (GPLv3)
Classifier: Operating System :: OS Independent
Requires-Python: >=3.10
License-File: LICENSE
Requires-Dist: autograd
Requires-Dist: matplotlib
Requires-Dist: astropy
Requires-Dist: scipy
